Metadata-Version: 2.1
Name: exam-angel
Version: 1.0.1
Summary: Opis biblioteki exam_angel
Home-page: UNKNOWN
Author: Matty_Mroz
Author-email: mateuszmroz001@gmail.com
License: MIT
Platform: UNKNOWN
License-File: LICENSE.txt
